ostruct/__init__.py
ostruct/cli/__init__.py
ostruct/cli/attachment_processor.py
ostruct/cli/attachment_template_bridge.py
ostruct/cli/base_errors.py
ostruct/cli/binary_detector.py
ostruct/cli/cache_config.py
ostruct/cli/cache_manager.py
ostruct/cli/cache_utils.py
ostruct/cli/cli.py
ostruct/cli/click_options.py
ostruct/cli/code_interpreter.py
ostruct/cli/commands/__init__.py
ostruct/cli/commands/files.py
ostruct/cli/commands/list_models.py
ostruct/cli/commands/models.py
ostruct/cli/commands/run.py
ostruct/cli/commands/runx.py
ostruct/cli/commands/scaffold.py
ostruct/cli/commands/setup.py
ostruct/cli/commands/update_registry.py
ostruct/cli/config.py
ostruct/cli/constants.py
ostruct/cli/container_downloader.py
ostruct/cli/cost_estimation.py
ostruct/cli/download_errors.py
ostruct/cli/download_logger.py
ostruct/cli/errors.py
ostruct/cli/exit_codes.py
ostruct/cli/explicit_file_processor.py
ostruct/cli/field_utils.py
ostruct/cli/file_info.py
ostruct/cli/file_list.py
ostruct/cli/file_search.py
ostruct/cli/file_utils.py
ostruct/cli/gitignore_support.py
ostruct/cli/help_json.py
ostruct/cli/json_extract.py
ostruct/cli/json_limits.py
ostruct/cli/mcp_integration.py
ostruct/cli/model_creation.py
ostruct/cli/model_validation.py
ostruct/cli/ost/__init__.py
ostruct/cli/ost/arg_policy.py
ostruct/cli/ost/frontmatter.py
ostruct/cli/ost/schema_export.py
ostruct/cli/ost/windows_launcher.py
ostruct/cli/params.py
ostruct/cli/path_utils.py
ostruct/cli/plan_assembly.py
ostruct/cli/plan_printing.py
ostruct/cli/progress.py
ostruct/cli/progress_reporting.py
ostruct/cli/quick_ref_help.py
ostruct/cli/registry_updates.py
ostruct/cli/render_context.py
ostruct/cli/retry_handler.py
ostruct/cli/rich_config.py
ostruct/cli/runner.py
ostruct/cli/runx/__init__.py
ostruct/cli/runx/__main__.py
ostruct/cli/runx/runx_main.py
ostruct/cli/runx/runx_main_argparse.py
ostruct/cli/safe_regex.py
ostruct/cli/schema_utils.py
ostruct/cli/schema_validation.py
ostruct/cli/security/__init__.py
ostruct_cli-1.6.1.dist-info/LICENSE
ostruct_cli-1.6.1.dist-info/METADATA
ostruct_cli-1.6.1.dist-info/WHEEL
ostruct_cli-1.6.1.dist-info/entry_points.txt
ostruct_cli-1.6.1.dist-info/RECORD
