Metadata-Version: 2.3
Name: ostruct-cli
Version: 1.6.1
Summary: CLI for OpenAI Structured Output with Multi-Tool Integration
Author: Yaniv Golan
Author-email: yaniv@golan.name
Requires-Python: >=3.10,<4.0
Classifier: Programming Language :: Python :: 3
Classifier: Programming Language :: Python :: 3.10
Classifier: Programming Language :: Python :: 3.11
Classifier: Programming Language :: Python :: 3.12
Classifier: Programming Language :: Python :: 3.13
Provides-Extra: docs
Provides-Extra: enhanced-detection
Provides-Extra: examples
Requires-Dist: asyncio-throttle (>=1.0.2,<2.0) ; extra == "examples"
Requires-Dist: bleach (>=6.0.0,<7.0)
Requires-Dist: cachetools (>=5.3.2,<6.0)
Requires-Dist: chardet (>=5.0.0,<6.0)
Requires-Dist: click (>=8.2.1,<9.0)
Requires-Dist: ijson (>=3.2.3,<4.0)
Requires-Dist: jinja2 (>=3.1.2,<4.0)
Requires-Dist: jsonschema (>=4.23.0,<5.0)
Requires-Dist: magika (>=0.5.0,<1.0) ; extra == "enhanced-detection"
Requires-Dist: myst-parser (>=4.0.1,<5.0)
Requires-Dist: myst-parser (>=4.0.1,<5.0) ; extra == "docs"
Requires-Dist: openai (==1.81.0)
Requires-Dist: openai-model-registry (>=0.7.0,<1.0)
Requires-Dist: pathspec (>=0.12.1,<0.13.0)
Requires-Dist: pydantic (>=2.6.3,<3.0)
Requires-Dist: pygments (>=2.15.0,<3.0)
Requires-Dist: python-dotenv (>=1.0.1,<2.0)
Requires-Dist: pyyaml (>=6.0.2,<7.0)
Requires-Dist: questionary (>=2.0.0,<3.0.0)
Requires-Dist: rich (>=13.0.0,<14.0.0)
Requires-Dist: rich-click (>=1.8.9,<2.0.0)
Requires-Dist: sphinx (>=7.0.0,<9.0) ; extra == "docs"
Requires-Dist: sphinx-design (>=0.6.1,<1.0)
Requires-Dist: sphinx-design (>=0.6.1,<1.0) ; extra == "docs"
Requires-Dist: sphinx-rtd-theme (>=3.0,<4.0) ; extra == "docs"
Requires-Dist: tabulate (>=0.9.0,<0.10.0)
Requires-Dist: tenacity (>=8.2.3,<9.0) ; extra == "examples"
Requires-Dist: tiktoken (==0.9.0)
Requires-Dist: tomli (>=2.0.1,<3.0) ; (python_version < "3.11") and (extra == "docs")
Requires-Dist: tomli (>=2.0.1,<3.0) ; python_version < "3.11"
Requires-Dist: typing-extensions (>=4.9.0,<5.0)
Requires-Dist: werkzeug (>=3.1.3,<4.0)
